MANIFEST.in
README.rst
setup.cfg
setup.py
tests/__init__.py
tests/base.py
tests/test_controller.py
tests/test_controller_auth.py
tests/controllers/__init__.py
tests/controllers/root.py
tests/templates/__init__.py
tgapp_userprofile.egg-info/PKG-INFO
tgapp_userprofile.egg-info/SOURCES.txt
tgapp_userprofile.egg-info/dependency_links.txt
tgapp_userprofile.egg-info/entry_points.txt
tgapp_userprofile.egg-info/not-zip-safe
tgapp_userprofile.egg-info/requires.txt
tgapp_userprofile.egg-info/top_level.txt
userprofile/__init__.py
userprofile/bootstrap.py
userprofile/helpers.py
userprofile/partials.py
userprofile/controllers/__init__.py
userprofile/controllers/root.py
userprofile/i18n/userprofile.pot
userprofile/i18n/en/LC_MESSAGES/userprofile.mo
userprofile/i18n/en/LC_MESSAGES/userprofile.po
userprofile/i18n/it/LC_MESSAGES/userprofile.mo
userprofile/i18n/it/LC_MESSAGES/userprofile.po
userprofile/lib/__init__.py
userprofile/model/__init__.py
userprofile/model/ming/__init__.py
userprofile/model/ming/models.py
userprofile/model/sqla/__init__.py
userprofile/model/sqla/models.py
userprofile/public/__init__.py
userprofile/public/css/style.css
userprofile/public/images/default_avatar.jpg
userprofile/public/images/star.png
userprofile/templates/__init__.py
userprofile/templates/edit.xhtml
userprofile/templates/index.xhtml