Metadata-Version: 2.1
Name: tgapp-userprofile
Version: 0.3.6
Summary: Pluggable application for TurboGears2 which provides a basic user profile page with forms to allow users to edit their own profile or change their email/password
Home-page: https://github.com/axant/tgapp-userprofile
Author: Mirko Darino, Alessandro Molina, Vincenzo Castiglia, Marco Bosio
Author-email: mirko.darino@axant.it, alessandro.molina@axant.it, vincenzo.castiglia@axant.it, marco.bosio@axant.it
License: UNKNOWN
Keywords: turbogears2.application
Platform: UNKNOWN
Provides-Extra: testing
